langchain_tzafon/__init__.py
langchain_tzafon/chat_tzafon.py
langchain_tzafon/constants.py
langchain_tzafon/core.py
langchain_tzafon/tzafon_loader.py
langchain_tzafon/utils.py
langchain_tzafon-1.1.1.dist-info/METADATA
langchain_tzafon-1.1.1.dist-info/WHEEL
langchain_tzafon-1.1.1.dist-info/entry_points.txt
langchain_tzafon-1.1.1.dist-info/RECORD
