Metadata-Version: 2.4
Name: langchain-tzafon
Version: 1.1.1
Summary: An integration package connecting Tzafon and LangChain
Requires-Python: >=3.11
Requires-Dist: dotenv>=0.9.9
Requires-Dist: langchain-core>=1.2.7
Requires-Dist: openai>=2.15.0
Requires-Dist: playwright>=1.57.0
Requires-Dist: pydantic-settings>=2.12.0
Requires-Dist: pydantic>=2.12.5
Requires-Dist: tzafon>=2.18.0
